fastapi_oidc/__init__.py
fastapi_oidc/auth.py
fastapi_oidc/discovery.py
fastapi_oidc/exceptions.py
fastapi_oidc/types.py
fastapi_oidc-0.0.10.dist-info/LICENSE
fastapi_oidc-0.0.10.dist-info/WHEEL
fastapi_oidc-0.0.10.dist-info/METADATA
fastapi_oidc-0.0.10.dist-info/RECORD
