Metadata-Version: 2.1
Name: fastapi-oidc
Version: 0.0.10
Summary: A simple library for parsing and verifying externally issued OIDC ID tokens in fastapi.
Home-page: https://github.com/HarryMWinters/fastapi-oidc
License: MIT
Author: HarryMWinters
Author-email: harrymcwinters@gmail.com
Requires-Python: >=3.10,<4.0
Classifier: License :: OSI Approved :: MIT License
Classifier: Programming Language :: Python :: 3
Classifier: Programming Language :: Python :: 3.10
Classifier: Programming Language :: Python :: 3.11
Requires-Dist: cachetools (>=4.1.1)
Requires-Dist: fastapi (>=0.61.0)
Requires-Dist: pydantic (>=2.0.0)
Requires-Dist: python-jose[cryptography] (>=3.2.0)
Requires-Dist: requests (>=2.24.0)
Project-URL: Documentation, https://fastapi-oidc.readthedocs.io/en/latest/
Project-URL: Repository, https://github.com/HarryMWinters/fastapi-oidc
